{"coord":{"lon":73.36,"lat":54.99},"weather":[{"id":620,"main":"Snow","description":"light shower snow","icon":"13n"}],"base":"stations","main":{"temp":-3.96,"feels_like":-10.96,"temp_min":-3.96,"temp_max":-3.96,"pressure":1008,"humidity":80,"sea_level":1008,"grnd_level":997},"visibility":8000,"wind":{"speed":8,"deg":360,"gust":14},"clouds":{"all":75},"dt":1762718144,"sys":{"type":1,"id":8960,"country":"RU","sunrise":1762741694,"sunset":1762773167},"timezone":21600,"id":1496153,"name":"Omsk","cod":200}