{"coord":{"lon":73.36,"lat":54.99},"weather":[{"id":600,"main":"Snow","description":"light snow","icon":"13n"}],"base":"stations","main":{"temp":-10.96,"feels_like":-17.96,"temp_min":-10.96,"temp_max":-10.96,"pressure":1017,"humidity":73,"sea_level":1017,"grnd_level":1007},"visibility":2600,"wind":{"speed":10,"deg":240},"snow":{"1h":0.4},"clouds":{"all":75},"dt":1766357748,"sys":{"type":1,"id":8960,"country":"RU","sunrise":1766374204,"sunset":1766400000},"timezone":21600,"id":1496153,"name":"Omsk","cod":200}