{"coord":{"lon":73.36,"lat":54.99},"weather":[{"id":802,"main":"Clouds","description":"scattered clouds","icon":"03n"}],"base":"stations","main":{"temp":-10.96,"feels_like":-15.22,"temp_min":-10.96,"temp_max":-10.96,"pressure":1021,"humidity":85,"sea_level":1021,"grnd_level":1010},"visibility":10000,"wind":{"speed":2,"deg":200},"clouds":{"all":40},"dt":1739325999,"sys":{"type":1,"id":8960,"country":"RU","sunrise":1739327761,"sunset":1739361945},"timezone":21600,"id":1496153,"name":"Omsk","cod":200}