{"coord":{"lon":73.36,"lat":54.99},"weather":[{"id":600,"main":"Snow","description":"light snow","icon":"13d"},{"id":701,"main":"Mist","description":"mist","icon":"50d"}],"base":"stations","main":{"temp":-0.96,"feels_like":-5.46,"temp_min":-0.96,"temp_max":-0.96,"pressure":1018,"humidity":93,"sea_level":1018,"grnd_level":1007},"visibility":2900,"wind":{"speed":4,"deg":200},"clouds":{"all":100},"dt":1762426546,"sys":{"type":1,"id":8960,"country":"RU","sunrise":1762395604,"sunset":1762428017},"timezone":21600,"id":1496153,"name":"Omsk","cod":200}