{"coord":{"lon":73.36,"lat":54.99},"weather":[{"id":802,"main":"Clouds","description":"scattered clouds","icon":"03n"}],"base":"stations","main":{"temp":-7.96,"feels_like":-14.96,"temp_min":-7.96,"temp_max":-7.96,"pressure":1030,"humidity":79,"sea_level":1030,"grnd_level":1020},"visibility":10000,"wind":{"speed":6,"deg":170},"clouds":{"all":40},"dt":1734386145,"sys":{"type":1,"id":8960,"country":"RU","sunrise":1734406030,"sunset":1734431902},"timezone":21600,"id":1496153,"name":"Omsk","cod":200}