{"coord":{"lon":73.36,"lat":54.99},"weather":[{"id":500,"main":"Rain","description":"light rain","icon":"10n"}],"base":"stations","main":{"temp":17.31,"feels_like":17.19,"temp_min":17.31,"temp_max":17.31,"pressure":1006,"humidity":80,"sea_level":1006,"grnd_level":997},"visibility":10000,"wind":{"speed":3.48,"deg":208,"gust":9.36},"rain":{"1h":0.38},"clouds":{"all":100},"dt":1783892075,"sys":{"country":"RU","sunrise":1783896271,"sunset":1783957175},"timezone":21600,"id":1496153,"name":"Omsk","cod":200}