{"coord":{"lon":73.36,"lat":54.99},"weather":[{"id":701,"main":"Mist","description":"mist","icon":"50n"},{"id":620,"main":"Snow","description":"light shower snow","icon":"13n"}],"base":"stations","main":{"temp":-7.96,"feels_like":-11.73,"temp_min":-7.96,"temp_max":-7.96,"pressure":1024,"humidity":93,"sea_level":1024,"grnd_level":1013},"visibility":4100,"wind":{"speed":2,"deg":360},"snow":{"1h":0.25},"clouds":{"all":75},"dt":1736269167,"sys":{"type":1,"id":8960,"country":"RU","sunrise":1736220533,"sunset":1736247375},"timezone":21600,"id":1496153,"name":"Omsk","cod":200}