{"coord":{"lon":73.36,"lat":54.99},"weather":[{"id":500,"main":"Rain","description":"light rain","icon":"10d"}],"base":"stations","main":{"temp":16.04,"feels_like":15.03,"temp_min":16.04,"temp_max":16.04,"pressure":1009,"humidity":51,"sea_level":1009,"grnd_level":999},"visibility":10000,"wind":{"speed":3,"deg":230},"rain":{"1h":0.54},"clouds":{"all":40},"dt":1779513991,"sys":{"type":1,"id":8960,"country":"RU","sunrise":1779490008,"sunset":1779549604},"timezone":21600,"id":1496153,"name":"Omsk","cod":200}